{
    "active": true,
    "children": [],
    "components": [
        {
            "active": true,
            "type": 23
        },
        {
            "active": true,
            "position": [
                0.0,
                0.0,
                36.57600021362305
            ],
            "rotation": [
                0.0,
                0.0,
                0.0,
                1.0
            ],
            "scale": [
                1.0,
                1.0,
                1.0
            ],
            "type": 21
        },
        {
            "active": true,
            "body_type": "Static",
            "freeze_position_x": false,
            "freeze_position_y": false,
            "freeze_position_z": false,
            "freeze_rotation_x": false,
            "freeze_rotation_y": false,
            "freeze_rotation_z": false,
            "mass": 1.0,
            "type": 6,
            "use_gravity": true
        },
        {
            "active": true,
            "center": [
                0.0,
                0.0,
                0.0
            ],
            "filter": "win_trigger",
            "is_trigger": true,
            "scale_factor": [
                14.600000381469727,
                4.900000095367432,
                2.0999999046325684
            ],
            "type": 7
        },
        {
            "active": true,
            "file_name": "Assets/Scripts/WinTrigger.lua",
            "id": 843379159,
            "inspector_variables": [
                {
                    "name": "sceneName",
                    "type": "string",
                    "value": "TransitionScreen"
                }
            ],
            "type": 5
        }
    ],
    "isPrefab": true,
    "name": "win_trigger",
    "tag": 0
}
